gooddata_flexconnect/__init__.py
gooddata_flexconnect/py.typed
gooddata_flexconnect/function/__init__.py
gooddata_flexconnect/function/data_source_messages.py
gooddata_flexconnect/function/execution_context.py
gooddata_flexconnect/function/flight_methods.py
gooddata_flexconnect/function/function.py
gooddata_flexconnect/function/function_invocation.py
gooddata_flexconnect/function/function_registry.py
gooddata_flexconnect/function/function_task.py
gooddata_flexconnect-1.58.0.dist-info/METADATA
gooddata_flexconnect-1.58.0.dist-info/WHEEL
gooddata_flexconnect-1.58.0.dist-info/licenses/LICENSE.txt
gooddata_flexconnect-1.58.0.dist-info/RECORD
